backend/__init__.py
backend/app.py
backend/cli.py
backend/db.py
backend/validation.py
backend/ws.py
backend/parser/parser.py
backend/solvers/abstract_solver.py
backend/solvers/numba_runner.py
backend/solvers/scipy_solver.py
backend/static/index.html
backend/static/assets/css.worker-Bx5KRiUl.js
backend/static/assets/editor-BRFsMTim.css
backend/static/assets/editor.api-CuPqX3i8.js
backend/static/assets/editor.worker-DogVlCF9.js
backend/static/assets/index-DNMhvDxX.css
backend/static/assets/index-Vl83zn32.js
backend/static/assets/json.worker-BthQ50h7.js
backend/static/assets/ts.worker-DaHRWH16.js
backend/worker/manager.py
equation_phase_portrait_tool/__init__.py
equation_phase_portrait_tool/__main__.py
equation_phase_portrait_tool/_version.py
equation_phase_portrait_tool/main.py
equation_phase_portrait_tool-0.1.0.dist-info/licenses/LICENSE
equation_phase_portrait_tool-0.1.0.dist-info/METADATA
equation_phase_portrait_tool-0.1.0.dist-info/WHEEL
equation_phase_portrait_tool-0.1.0.dist-info/entry_points.txt
equation_phase_portrait_tool-0.1.0.dist-info/top_level.txt
equation_phase_portrait_tool-0.1.0.dist-info/RECORD
