Metadata-Version: 2.4
Name: equation-phase-portrait-tool
Version: 0.1.0
Summary: Equation Phase Portrait Tool - local distribution
Requires-Python: >=3.8
License-File: LICENSE
Requires-Dist: fastapi
Requires-Dist: uvicorn[standard]
Requires-Dist: pydantic
Requires-Dist: numpy
Requires-Dist: scipy
Requires-Dist: aiohttp
Requires-Dist: websockets
Requires-Dist: python-multipart
Requires-Dist: aiofiles
Provides-Extra: numba
Requires-Dist: numba; extra == "numba"
Provides-Extra: dev
Requires-Dist: build; extra == "dev"
Requires-Dist: twine; extra == "dev"
Requires-Dist: wheel; extra == "dev"
Requires-Dist: pytest; extra == "dev"
Requires-Dist: pytest-asyncio; extra == "dev"
Requires-Dist: requests; extra == "dev"
Dynamic: license-file
